{
  "collapse-filter": false,
  "search": "path:\"200 Proyectos/Bases de datos\"  ",
  "showTags": false,
  "showAttachments": false,
  "hideUnresolved": false,
  "showOrphans": true,
  "collapse-color-groups": false,
  "colorGroups": [
    {
      "query": "path:\"200 Proyectos/Bases de datos/_Archive\"  ",
      "color": {
        "a": 1,
        "rgb": 11657298
      }
    }
  ],
  "collapse-display": false,
  "showArrow": false,
  "textFadeMultiplier": 0,
  "nodeSizeMultiplier": 1,
  "lineSizeMultiplier": 1,
  "collapse-forces": false,
  "centerStrength": 0.2578125,
  "repelStrength": 15.46875,
  "linkStrength": 1,
  "linkDistance": 112,
  "scale": 0.18462326225858,
  "close": false
}